pyrkafka-0.1.1.dist-info/METADATA
pyrkafka-0.1.1.dist-info/WHEEL
pyrkafka/__init__.py
pyrkafka/pyrkafka.abi3.so
pyrkafka-0.1.1.dist-info/RECORD
