Metadata-Version: 2.3
Name: pyrkafka
Version: 0.1.1
Classifier: Programming Language :: Rust
Classifier: Programming Language :: Python :: Implementation :: CPython
Classifier: Programming Language :: Python :: Implementation :: PyPy
Summary: Python bindings for rdfkafka Rust library
Author-email: Michael Rademaker <michael@appbriek.com>
License: MIT License
Requires-Python: >=3.8
Project-URL: Homepage, https://github.com/Miggets7/pyrkafka
Project-URL: Documentation, https://github.com/Miggets7/pyrkafka
Project-URL: Repository, https://github.com/Miggets7/pyrkafka
Project-URL: Issues, https://github.com/Miggets7/pyrkafka/issues
Project-URL: Changelog, https://github.com/Miggets7/pyrkafka
